usps_track/__init__.py
usps_track/__main__.py
usps_track/constants.py
usps_track/lib.py
usps_track/main.py
usps_track/py.typed
usps_track/utils.py
usps_track-0.0.3.dist-info/METADATA
usps_track-0.0.3.dist-info/WHEEL
usps_track-0.0.3.dist-info/entry_points.txt
usps_track-0.0.3.dist-info/licenses/LICENSE.txt
usps_track-0.0.3.dist-info/RECORD
