Metadata-Version: 2.4
Name: usps-track
Version: 0.0.3
Summary: Quickly track via SMS several USPS (and some international) tracking numbers via the command line.
License-Expression: MIT
License-File: LICENSE.txt
Keywords: command line,shipping,usps
Author: Andrew Udvare
Author-email: audvare@gmail.com
Requires-Python: >=3.10,<4.0
Classifier: Development Status :: 4 - Beta
Classifier: Intended Audience :: Developers
Classifier: Programming Language :: Python
Classifier: Programming Language :: Python :: 3.10
Classifier: Programming Language :: Python :: 3.11
Classifier: Programming Language :: Python :: 3.12
Classifier: Programming Language :: Python :: 3.13
Classifier: Programming Language :: Python :: 3.14
Classifier: Typing :: Typed
Requires-Dist: aiohttp (>=3.13.2,<4.0.0)
Requires-Dist: bascom (>=0.1.0,<0.2.0)
Requires-Dist: click (>=8.3.1,<9.0.0)
Requires-Dist: typing-extensions (>=4.15.0,<5.0.0)
Project-URL: Documentation, https://usps-track.readthedocs.org
Project-URL: Homepage, https://tatsh.github.io/usps-track/
Project-URL: Issues, https://github.com/Tatsh/usps-track/issues
Project-URL: Repository, https://github.com/Tatsh/usps-track
